wsc/__init__.py
wsc/wsc.py
web_source_compiler-0.0.3.dist-info/METADATA
web_source_compiler-0.0.3.dist-info/WHEEL
web_source_compiler-0.0.3.dist-info/entry_points.txt
web_source_compiler-0.0.3.dist-info/top_level.txt
web_source_compiler-0.0.3.dist-info/RECORD
