Metadata-Version: 2.1
Name: web-source-compiler
Version: 0.0.3
Summary: A package for reading Jenkinsfile-like pipeline files
Home-page: https://github.com/jfcarter2358/web-source-compiler
Author: John Carter
Author-email: jfcarter2358@gmail.com
License: UNKNOWN
Project-URL: Bug Tracker, https://github.com/jfcarter2358/web-source-compiler/issues
Platform: UNKNOWN
Classifier: Programming Language :: Python :: 3
Classifier: License :: OSI Approved :: MIT License
Classifier: Operating System :: OS Independent
Requires-Python: >=3.8
Requires-Dist: cartils (==0.1.1)
Requires-Dist: setuptools (==41.2.0)
